sine.properties-0.1.0-py2.7-nspkg.pth
sine/properties/__init__.py
sine/properties/__version__.py
sine/properties/core.py
sine/properties/properties_tests.py
sine/properties/tests.py
sine.properties-0.1.0.dist-info/DESCRIPTION.rst
sine.properties-0.1.0.dist-info/METADATA
sine.properties-0.1.0.dist-info/RECORD
sine.properties-0.1.0.dist-info/WHEEL
sine.properties-0.1.0.dist-info/metadata.json
sine.properties-0.1.0.dist-info/namespace_packages.txt
sine.properties-0.1.0.dist-info/top_level.txt
